ucl_sdk/__init__.py
ucl_sdk/client.py
ucl_sdk/py.typed
ucl_sdk/types.py
ucl_tools-1.0.0.dist-info/METADATA
ucl_tools-1.0.0.dist-info/WHEEL
ucl_tools-1.0.0.dist-info/top_level.txt
ucl_tools-1.0.0.dist-info/RECORD
